LICENSE
tonkatsu/__init__.py
tonkatsu/py.typed
tonkatsu-0.1.0.dist-info/LICENSE
tonkatsu-0.1.0.dist-info/WHEEL
tonkatsu-0.1.0.dist-info/METADATA
tonkatsu-0.1.0.dist-info/RECORD
