Metadata-Version: 2.1
Name: tonkatsu
Version: 0.1.0
Summary: An asynchronous and lightweight wrapper around the anilist GraphQL API
Home-page: https://github.com/AbstractUmbra/tonkatsu
License: MIT
Keywords: anilist,graphql,wrapper,api
Author: Alex Nørgaard
Author-email: Umbra@AbstractUmbra.dev
Requires-Python: >=3.10,<4.0
Classifier: Intended Audience :: Developers
Classifier: License :: OSI Approved :: MIT License
Classifier: Natural Language :: English
Classifier: Operating System :: OS Independent
Classifier: Programming Language :: Python :: 3
Classifier: Programming Language :: Python :: 3.10
Classifier: Topic :: Internet
Classifier: Typing :: Typed
Provides-Extra: docs
Requires-Dist: aiohttp (>=3.8.1,<4.0.0)
Requires-Dist: furo; extra == "docs"
Requires-Dist: sphinx (>=4.0.0,<5.0.0); extra == "docs"
Requires-Dist: sphinxcontrib-trio; extra == "docs"
Project-URL: Discord, https://discord.gg/aYGYJxwqe5
Project-URL: Issue Tracker, https://github.com/AbstractUmbra/tonkatsu/issues
Project-URL: Repository, https://github.com/AbstractUmbra/tonkatsu
